[
    {
        "title": "Achtung, fertig, Zähneputzen!",
        "figure": "Leos Tag",
        "description": "Bli-bla-blitzeblanke Zähne! Unser kleiner Leopard hat meistens mehr spannende Dinge im Kopf als Punkte auf seinem Fell. Da ist es gut, dass seine magische Zahnbürste Elli ihn immer wieder freundlich erinnert, dass auch kleine Leoparden ihre Beißerchen putzen müssen. Und zwischen den Kapiteln können die Kleinen selbst aktiv werden: Wenn einer der 8 tollen Songs ertönt, heißt es „Ohren spitzen und mitputzen“! Denn diese sind so konzipiert, dass Kinder „spielend“ die erforderlichen zwei Minuten bürsten. In diesem Mix aus Geschichten und Liedern hilft Leo den Kindern vor allem Spaß zu haben – ob beim „Wackelzahn-Wackelalarm“, dem Zahnfee-Gedicht oder dem Gurgel-Song“.",
        "titlelist": [
            "01 - Los geht's!",
            "02 - Bli-bla-blitzeblanke Zähne",
            "03 - \"Süße\" Tierchen in deinem Mund?",
            "04 - Ellis Reise",
            "05 - Armer, kleiner Leo",
            "06 - Quatsch im Badezimmmer",
            "07 - Leoparden-lecker, aber gut für die Zähne?",
            "08 - Da wackelt was!",
            "09 - Keine Angst, Leo!",
            "10 - In geheimer Mission",
            "11 - Leo und Ellli haben Streit"
        ],
        "runtime": "ca. 50 Minuten",
        "age_recommendation": "Ab 3 Jahre",
        "image": "https://res.cloudinary.com/tonies/image/fetch/f_auto,q_auto,c_fill,b_rgb:ffffff,w_1000,h_1200/https://278163f382d2bab4b036-4f5ec62496a160f3570d3b6e48fc4516.ssl.cf3.rackcdn.com/10001473-50004892-b-CH2wvqo-.png"
    },
    {
        "title": "Gute Nacht, kleine Eule",
        "figure": "Die Eule mit der Beule",
        "description": "Gute Nacht, kleine Eule, es ist Schlafenszeit. Warte noch, Mama, ich bin gleich so weit. Die kleine Eule kann noch nicht schlafen. Was hilft da nur? Ein wohlig warmes Bad? Nein! Ein Schlaflied? Auch nicht! Denn am Ende hilft nur eins: der Gutenachtkuss von Mama.",
        "titlelist": [
            "01 - Gute Nacht, kleine Eule (Lied)",
            "02 - Besuch beim Biber",
            "03 - Die kleine Eule fliegt zu den Sternen",
            "04 - Die kleine Eule fliegt zu den Sternen (Lied)",
            "05 - Post für den Spatz",
            "06 - Die kleine Eule findet einen Freund",
            "07 - Die kleine Eule findet einen Freund (Lied)",
            "08 - Ein Tag mit Papa",
            "09 - Pssst! Die kleine Eule will schlafen",
            "10 - Das Waldorchester-Lied (Lied)",
            "11 - Pssst! Die kleine Eule will schlafen (Lied)",
            "12 - Gute Nacht, kleine Eule (Lied: Instrumental-Version)"
        ],
        "runtime": "ca. 49 Minuten",
        "age_recommendation": "Ab 3 Jahre",
        "image": "https://res.cloudinary.com/tonies/image/fetch/f_auto,q_auto,c_fill,b_rgb:ffffff,w_1000,h_1200/https://278163f382d2bab4b036-4f5ec62496a160f3570d3b6e48fc4516.ssl.cf3.rackcdn.com/10001489-50004782-b-xfVCE7Y5.png"
    },
    {
        "title": "Furzipups - 3 Geschichten und 6 Songs",
        "figure": "Furzipups, der Knatterdrache",
        "description": "Ein furzender Drache, ein hicksendes Huhn und ein rülpsendes Mammut - alle zusammen auf einem Tonie und alle aus der Feder des Bestseller-Autors Kai Lüftner. Und wie könnte es anders sein, so hat der Erfinder von ROTZN ROLL RADIO sich natürlich nicht lumpen lassen und neben den drei Geschichten auch noch sechs passende Lieder geschrieben und höchst persönlich eingesungen.Auf diesem Tonie:Furzipups, der KnatterdracheFurzipups und Hicksi HuhnFurzipups und Rüdiger Rülps Rüsselplus 6 Songsgelesen und gesungen von Kai Lüftner",
        "titlelist": [
            "01 - Furzen in der Badewanne",
            "02 - Furzipups der Knatterdrache",
            "03 - Alles ist Musik",
            "04 - Mach es richtig",
            "05 - Furzipups und Hicksihuhn",
            "06 - Frag mich nicht",
            "07 - Die dicken Jungs",
            "08 - Furzipups und Rüdiger Rülpsrüssel",
            "09 - Wiedersehn",
            "10 - Introducing Karaoke",
            "11 - Furzen in der Badewanne (Karaoke Version)",
            "12 - Alles ist Musik (Karaoke Version)",
            "13 - Mach es richtig (Karaoke Version)",
            "14 - Frag mich nicht (Karaoke Version)",
            "15 - Die dicken Jungs (Karaoke Version)",
            "16 - Wiedersehn (Karaoke Version)",
            "17 - Outro und Hidden Furz (Karaoke Version)"
        ],
        "runtime": "ca. 50 Minuten",
        "age_recommendation": "Ab 3 Jahre",
        "image": "https://res.cloudinary.com/tonies/image/fetch/f_auto,q_auto,c_fill,b_rgb:ffffff,w_1000,h_1200/https://278163f382d2bab4b036-4f5ec62496a160f3570d3b6e48fc4516.ssl.cf3.rackcdn.com/10001675-50005288-b-aNIpZYNe.png"
    },
    {
        "title": "Seine ersten Abenteuer",
        "figure": "Nasreddin Hodscha",
        "description": "Der orientalische Schelm Nasreddin Hodscha ist nicht nur in der Türkei und in ganz Asien für seinen tiefgründigen Humor bekannt. Jetzt bezaubert er auch ohne weißen Bart - mehr als 20 seiner lustigsten Anekdoten, kindgerecht und modern für Kinder von heute nacherzählt, regen sowohl zum Lachen als auch zum Nachdenken an.Der schlagfertige Junge mit dem Spitznamen Nasri will Hodscha werden. Doch für eine Gelehrtenausbildung muss er erst einmal an der Schule in Konya angenommen werden. Zum Glück kann Nasri auf die Unterstützung seiner mutigen Freundin Elif bauen. Auf dem Weg in die Großstadt überwältigen sie Diebe, überlisten Herrscher und erleben verrückte Abenteuer mit Elefanten …Türkische Audioversion über mytonies für € 1,99 erhätllich!",
        "titlelist": [
            "01 - Vor langer langer Zeit …",
            "02 - Große Träume",
            "03 - Wer ist denn dieses Mädchen?",
            "04 - Der denkende Truthahn",
            "05 - Die Rettung des Mondes und der Dieb",
            "06 - Die Reise beginnt",
            "07 - Der Freund mit den langen Ohren",
            "08 - Auch Sultane waschen sich",
            "09 - Die knauserige Fatma",
            "10 - Der Tag der Prüfung",
            "11 - Nasri gibt nicht auf!",
            "12 - Auf dem Rücken des Elefanten"
        ],
        "runtime": "ca. 85 Minuten",
        "age_recommendation": "Ab 5 Jahre",
        "image": "https://res.cloudinary.com/tonies/image/fetch/f_auto,q_auto,c_fill,b_rgb:ffffff,w_1000,h_1200/https://278163f382d2bab4b036-4f5ec62496a160f3570d3b6e48fc4516.ssl.cf3.rackcdn.com/10001488-50004778-b-gQ5yZIG5.png"
    },
    {
        "title": "Woohoo! / Die Suche nach Atlantis",
        "figure": "Disney",
        "description": "Woo-Hoo!: Weil Donald zu einem Vorstellungsgespräch geht, bringt er seine Neffen zu Onkel Dagobert. Gemeinsam mit Nicky, der Enkelin von Dagoberts Haushälterin, erforschen Tick, Trick und Track die Duck-Villa. Sie entdecken magische Erinnerungsstücke voller Geister und Dämonen, die jederzeit wieder lebendig werden können. Und einige tun das auch – wie der goldfressende Drache Pixiu …Die Suche nach Atlantis:Onkel Dagobert bricht mit den Kindern zu einer Tiefsee-Expedition auf, um den magischen Rubin von Atlantis zu erbeuten. Als die Ducks in das versunkene Reich gelangen, erkennen Sie, dass ihnen der teuflische Moneysack eine Falle gestellt hat, aus der es so leicht kein Entrinnen gibt …",
        "titlelist": [
            "01 - Titelsong",
            "02 - Woohoo! Kapitel 01",
            "03 - Woohoo! Kapitel 02",
            "04 - Woohoo! Kapitel 03",
            "05 - Die Suche nach Atlantis Kapitel 01",
            "06 - Die Suche nach Atlantis Kapitel 02",
            "07 - Die Suche nach Atlantis Kapitel 03"
        ],
        "runtime": "ca. 58 Minuten",
        "age_recommendation": "Ab 4 Jahre",
        "image": "https://res.cloudinary.com/tonies/image/fetch/f_auto,q_auto,c_fill,b_rgb:ffffff,w_1000,h_1200/https://278163f382d2bab4b036-4f5ec62496a160f3570d3b6e48fc4516.ssl.cf3.rackcdn.com/10001396-50004788-b-6xQXsQG1.png"
    },
    {
        "title": "Die Junghexenbande",
        "figure": "Bibi Blocksberg",
        "description": "Der Bürgermeister plant ein Motorboot-Rennen. Und der Wendepunkt der Strecke soll ausgerechnet die Naturschutz-Insel im Fluss sein, der Geheimtreffpunkt der Junghexen! Das bedroht die dortigen Tiere und Pflanzen. Um gegen diese Idee vorzugehen, gründet Bibi mit ihren Hexenfreundinnen die „Junghexenbande“. Das gefällt dem Stadtoberhaupt gar nicht.",
        "titlelist": [
            "01 - Die Junghexenbande"
        ],
        "runtime": "ca. 40 Minuten",
        "age_recommendation": "Ab 4 Jahre",
        "image": "https://res.cloudinary.com/tonies/image/fetch/f_auto,q_auto,c_fill,b_rgb:ffffff,w_1000,h_1200/https://278163f382d2bab4b036-4f5ec62496a160f3570d3b6e48fc4516.ssl.cf3.rackcdn.com/10001998-50006236-b-YC2jqSE6.png"
    },
    {
        "title": "Ein unwiderschlumpfliches Lächeln & 3 weitere schlumpfige Abenteuer",
        "figure": "Die Schlümpfe",
        "description": "Die, blauen Schlümpfe sind zurück und sie schlumpfen nicht allein: Aus dem verlorenen Dorf kommen auch die neuen weiblichen Schlümpfe mit in das Schlumpfdorf, wo sie sich zusammen mit Papa Schlumpf, Schlumpfine, Schlaubi und den anderen Schlümpfen in neue, witzige und überraschende Abenteuer stürzen. Immer wieder müssen sie sich dabei auch gegen den bösen Zauberer Gargamel und seinen Kater Azrael oder die gefräßigen Oger Großmaul und Eierkopf zu Wehr setzen.Die schlumpftastischen FünfJokey manipuliert die Wahl des Rettungsteams. Als Gargamel angreift, müssen Baby, Dummi, Clumsy, Fauli und Fürchti zeigen, dass sie zurecht gewählt wurden.Wer zuletzt lacht, …Durch einen Zauber wird Jokey vervielfacht. Schon bald treibt eine Horde Mini-Jokeys im Dorf Unfug. Können Jokey und Beauty dem Spuk ein Ende bereiten?Eine gefährliche EntwicklungAls Handys Windelwickler-Roboter mit Baby durchbrennt, nehmen Papa Schlumpf, Hefty, Handy, Muffi, Schlaubi und Jokey die Verfolgung auf.Ein unwiderschlumpfliches LächelnMit einem Ausflug will Schlumpfine Muffis schlechte Laune vertreiben - vergeblich. Zu allem Unglück bricht sich Muffi auch noch ein Bein. Was nun?",
        "titlelist": [
            "01 - Die schlumpftastischen Fünf",
            "02 - Wer zuletzt lacht,...",
            "03 - Eine gefährliche Entwicklung",
            "04 - Ein unwiderschlumpfliches Lächeln"
        ],
        "runtime": "ca. 50 Minuten",
        "age_recommendation": "Ab 5 Jahre",
        "image": "https://res.cloudinary.com/tonies/image/fetch/f_auto,q_auto,c_fill,b_rgb:ffffff,w_1000,h_1200/https://278163f382d2bab4b036-4f5ec62496a160f3570d3b6e48fc4516.ssl.cf3.rackcdn.com/10001677-50003915-b-C3OJyjcN.png"
    },
    {
        "title": "Ein tollpatschiger Held & 3 weitere schlumpfige Abenteuer",
        "figure": "Die Schlümpfe",
        "description": "Die blauen Schlümpfe sind zurück und sie schlumpfen nicht allein: Aus dem verlorenen Dorf kommen auch die neuen weiblichen Schlümpfe mit in das Schlumpfdorf, wo sie sich zusammen mit Papa Schlumpf, Schlumpfine, Schlaubi und den anderen Schlümpfen in neue, witzige und überraschende Abenteuer stürzen. Immer wieder müssen sie sich dabei auch gegen den bösen Zauberer Gargamel und seinen Kater Azrael oder die gefräßigen Oger Großmaul und Eierkopf zu Wehr setzen.Ein tollpatschiger HeldClumsy kann sich aus Gargamels Fängen befreien. Leider führt er den bösen Zauberer ins Dorf der Schlümpfe. Kann Clumsy seinen Fehler wieder gut machen?Wo ist Papa SchlumpfNach einer Explosion ist Papa Schlumpf unsichtbar. Für das Gegenmittel müssen er, Schlaubi und Schlumpfine ein Katzenschnurrhaar von Azrael besorgen.Der ferngesteuerte SpionFliegend soll Azrael für Gargamel das Schlumpfdorf finden. Als Sturmi und Handy ihn entdecken, schmieden die beiden einen wagemutigen Plan.Waffel-MittwochKoch ist frustriert, weil alle Lilys Waffeln lieber mögen, als seine. Er entführt Lilys Waffel-Wagen und droht damit eine Klippe hinab zu stürzen.",
        "titlelist": [
            "01 - Ein tollpatschiger Held",
            "02 - Wo ist Papa Schlumpf",
            "03 - Der ferngesteuerte Spion",
            "04 - Waffel-Mittwoch"
        ],
        "runtime": "ca. 50 Minuten",
        "age_recommendation": "Ab 5 Jahre",
        "image": "https://res.cloudinary.com/tonies/image/fetch/f_auto,q_auto,c_fill,b_rgb:ffffff,w_1000,h_1200/https://278163f382d2bab4b036-4f5ec62496a160f3570d3b6e48fc4516.ssl.cf3.rackcdn.com/10000478-50003911-b-iiVCaKHC.png"
    },
    {
        "title": "Bezaubernde Gutenachtgeschichten",
        "figure": "Gloria Glühwürmchen",
        "description": "Tief im Glitzerwald wohnt das kleine, aufgeweckte Glühwurmmädchen Gloria zusammen mit ihrer Familie und ihren Freunden. Sie ist ein ganz besonderes Glühwürmchen, denn nur Gloria lernt als einziges weibliches Glühwürmchen das Fliegen. Nachdem sie sich ihren großen Herzenswunsch erfüllt hat, saust sie Nacht für Nacht mit ihrer Libellenfreundin Lilly Belle durch den Glitzerwald und erlebt zehn zauberhafte Abenteuer.",
        "titlelist": [
            "01 - Gloria-Lied Intro",
            "02 - Gloria Glühwürmchen – das bin ich",
            "03 - Eine ganz besondere Nacht",
            "04 - Glühtag",
            "05 - Glühtag (Teil 2)",
            "06 - Ein großer Wunsch",
            "07 - Die Welt von oben",
            "08 - Die Welt von oben (Teil 2)",
            "09 - Vom Fliegen und Leuchten",
            "10 - Vom Fliegen und Leuchten (Teil 2)",
            "11 - Ausflug in die Menschenwelt",
            "12 - Ausflug in die Menschenwelt (Teil 2)",
            "13 - Glühtherapie für Igel Isidor",
            "14 - Geschichten vom Glühen",
            "15 - Geschichten vom Glühen (Teil 2)",
            "16 - Nachtwanderung mit Froschkonzert",
            "17 - Zauberhafte Freunde",
            "18 - Zauberhafte Freunde (Teil 2)",
            "19 - Gloria-Lied"
        ],
        "runtime": "ca. 128 Minuten",
        "age_recommendation": "Ab 4 Jahre",
        "image": "https://res.cloudinary.com/tonies/image/fetch/f_auto,q_auto,c_fill,b_rgb:ffffff,w_1000,h_1200/https://278163f382d2bab4b036-4f5ec62496a160f3570d3b6e48fc4516.ssl.cf3.rackcdn.com/10001483-50004756-b-UkvPZFOr.png"
    },
    {
        "title": "Na klar, Lotta kann Radfahren / Lotta zieht um",
        "figure": "Lotta",
        "description": "\"Na klar, Lotta kann Rad fahren\"Lotta ist fast fünf Jahre alt und wünscht sich zum Geburtstag nichtssehnlicher als ein Fahrrad. Sie hat nämlich nur ein altes Dreirad, und auf dem kann man schließlich nicht richtig fahren! Doch als der Geburtstag da ist, bekommt Lotta zwar viele schöne Geschenke, aber ein Fahrrad ist nicht dabei. Also muss Lotta sich etwas einfallen lassen …\"Lotta zieht um\"Als Lotta aus der Krachmacherstraße eines Morgens den kratzigen Pullover von ihrer Oma anziehen soll, wird sie richtig wütend. Erst schneidet sie ein großes Loch in den Pullover, und dann beschließt sie kurzerhand, von zu Hause auszuziehen. Nicht weit allerdings, nur zu Tante Berg nach nebenan. Denn Lotta möchte natürlich sehen, wie traurig alle sind, wenn sie keine Lotta mehr haben.\"",
        "titlelist": [
            "01 - Natürlich kann ich Rad fahren!“",
            "02 - Und dann legte Lotta los!",
            "03 - Alle sind gemein zu Lotta",
            "04 - Lotta, du kommst wohl gleich herunter…“",
            "05 - Lotta zieht aus",
            "06 - Wohin soll Lotta ziehen?",
            "07 - Lotta mietet eine Wohnung",
            "08 - Und Tante Berg schleppte ganz brav die Möbel herbei.",
            "09 - Lotta bekommt Besuch",
            "10 - Bin ich nachts so ganz allein"
        ],
        "runtime": "ca. 56 Minuten",
        "age_recommendation": "Ab 4 Jahre",
        "image": "https://res.cloudinary.com/tonies/image/fetch/f_auto,q_auto,c_fill,b_rgb:ffffff,w_1000,h_1200/https://278163f382d2bab4b036-4f5ec62496a160f3570d3b6e48fc4516.ssl.cf3.rackcdn.com/10000994-50003243-b-qYPLCYsh.png"
    },
    {
        "title": "Immer den Nüstern nach",
        "figure": "Die Haferhorde",
        "description": "Die Superponys sind zurück!Ein Wildschwein auf dem Blümchenhof? Sowas haben die Tiere hier noch nie gesehen. Aber der kleine Frischling Freddy hat seine Familie verloren – natürlich müssen Schoko und Keks ihm helfen, sie sind schließlich Superrettungsponys! Dabei haben sie eigentlich gerade ganz andere Sorgen: Die Chefin hat beschlossen, ein Springturnier zu veranstalten und auch die Pferde vom Donnerheini einzuladen. Und dann wird auf einmal ausgerechnet der gemütliche Toni von großem Ehrgeiz gepackt … Teil drei der turbulenten Reihe um die Ponys Schoko, Keks und ihre Freunde vom Blümchenhof – ungekürzt gelesen von Bürger Lars Dietrich.",
        "titlelist": [
            "01 - 49 Die Haferhorde: Immer den Nüstern nach"
        ],
        "runtime": "ca. 139 Minuten",
        "age_recommendation": "Ab 8 Jahre",
        "image": "https://res.cloudinary.com/tonies/image/fetch/f_auto,q_auto,c_fill,b_rgb:ffffff,w_1000,h_1200/https://278163f382d2bab4b036-4f5ec62496a160f3570d3b6e48fc4516.ssl.cf3.rackcdn.com/10001330-50004084-b-4e0R8fXC.png"
    },
    {
        "title": "Feuer im Wald",
        "figure": "Super Wings",
        "description": "Lukas hat sich einen Feuerwehrhelm bestellt. Den möchte er in der Schule tragen, wenn sein Vater von seiner Arbeit als Feuerwehrmann berichtet. Plötzlich steht der Wald gleich vor der Schule in Flammen. Die Schüler sehen zu, wie gelöscht wird. Jett eilt zu Hilfe und gemeinsam mit Lukas' Vater versucht er, ein kleines Rehkitz aus den Flammen zu retten. Doch ohne Unterstützung der Super Wings wird es Jett nicht schaffen können.",
        "titlelist": [
            "01 - Elefantenbabybad",
            "02 - Entlaufener Dinosaurier",
            "03 - Verlorene Fundstücke",
            "04 - Feuer im Wald"
        ],
        "runtime": "ca. 58 Minuten",
        "age_recommendation": "Ab 3 Jahre",
        "image": "https://res.cloudinary.com/tonies/image/fetch/f_auto,q_auto,c_fill,b_rgb:ffffff,w_1000,h_1200/https://278163f382d2bab4b036-4f5ec62496a160f3570d3b6e48fc4516.ssl.cf3.rackcdn.com/10001398-50004796-b-vpr1i_hI.png"
    },
    {
        "title": "Seemannsgarn",
        "figure": "Käpt'n Blaubär",
        "description": "Der sympathischste Lügenbär aller ZeitenKäpt‘n Blaubär erzählt seinen Enkeln nicht einfach nur Geschichten – er erfindet sie. Dabei ist er so kreativ und humorvoll, dass Legenden entstehen. Das spannende Spiel um Wahrheit oder Lüge betreibt der Seefahrer im Ruhestand zwar in Perfektion, er wird aber regelmäßig von seinen cleveren Enkeln des Lügens überführt. Nichtsdestotrotz lassen sich seine kleinen und großen Zuhörer begeistert auf exotische Reisen und in ferne Länder entführen.",
        "titlelist": [
            "01 - Käpt'n Seekrank und seine blöden Matrosen",
            "02 - Das Gespensterschiff",
            "03 - Die Piratencreme",
            "04 - Der Flaschengeist",
            "05 - Der Rock'n'Roll Kaiser von Pogo - Pogo",
            "06 - Atlantis",
            "07 - Der Zacken aus Neptuns Krone",
            "08 - Wellensalat",
            "09 - Superblödmann",
            "10 - Unter dem Maulwurfvulkan"
        ],
        "runtime": "ca. 50 Minuten",
        "age_recommendation": "Ab 4 Jahre",
        "image": "https://res.cloudinary.com/tonies/image/fetch/f_auto,q_auto,c_fill,b_rgb:ffffff,w_1000,h_1200/https://278163f382d2bab4b036-4f5ec62496a160f3570d3b6e48fc4516.ssl.cf3.rackcdn.com/10001409-50004888-b-lFs2YNLv.png"
    },
    {
        "title": "Oh Yeah!",
        "figure": "DIKKA",
        "description": "Rap für Erwachsene? Kann doch jedes Kind! Und ein ganz bestimmtes Nashorn kann das auch: DIKKA – das rappende Rhinozeros kommt auf seinem Debütalbum „Oh Yeah!“ mit jeder Menge wilder, frecher und lustiger Songs für starke Kinder. Groß, grau, gutgelaunt, mit dickem Bauch und ordentlich was in der Birne stellt DIKKA sich dabei nicht auf die Seite der Eltern, sondern nimmt die kleinen Hörer an die Hand und geht gemeinsam mit ihnen mal den wirklich wichtigen Fragen des Lebens nach.",
        "titlelist": [
            "01 - INTRO",
            "02 - PARTY IM ZOO",
            "03 - KANN ICH ALLEIN",
            "04 - SUPERPAPA FEAT. SIGGI",
            "05 - POMMES MIT MAYO",
            "06 - OH YEAH FEAT. FORSTI",
            "07 - ROLLE DURCH DEN KIEZ",
            "08 - KAKKA",
            "09 - GRAU",
            "10 - DIKKA KOMMA KLAR",
            "11 - ICH GEHV’ NICHT INS BETT",
            "12 - BIS ZUM MOND FEAT. LEA",
            "13 - BIS ZUM MOND (Instrumental)",
            "14 - BOOM SCHAKKALAKKA mit Wincent Weiß"
        ],
        "runtime": "ca. 36 Minuten",
        "age_recommendation": "Ab 5 Jahre",
        "image": "https://res.cloudinary.com/tonies/image/fetch/f_auto,q_auto,c_fill,b_rgb:ffffff,w_1000,h_1200/https://278163f382d2bab4b036-4f5ec62496a160f3570d3b6e48fc4516.ssl.cf3.rackcdn.com/10001685-50005326-b-HvtMeNAM.png"
    },
    {
        "title": "[EN] George Pig",
        "figure": "Peppa Pig",
        "description": "I speak English! Ich bin ein Tonie in englischer Sprache! Peppa Pig ist zurück mit zehn aufregenden neuen Abenteuern, die Ihre Kinder im Vorschulalter lieben werden. Begleiten Sie Peppa, George und ihre Familie und Freunde mit dieser neuen Audiosammlung, die eine vollständige Besetzung bekannter Stimmen, Musik und Spezialeffekte aus der TV-Serie Peppa Pig enthält.",
        "titlelist": [],
        "runtime": "ca. 59 Minuten",
        "age_recommendation": "Ab 3 Jahre",
        "image": "https://res.cloudinary.com/tonies/image/fetch/f_auto,q_auto,c_fill,b_rgb:ffffff,w_1000,h_1200/https://278163f382d2bab4b036-4f5ec62496a160f3570d3b6e48fc4516.ssl.cf3.rackcdn.com/10001231-50003758-b-ixcv5do-.png"
    },
    {
        "title": "Teil 1: Die große Suche",
        "figure": "Die unendliche Geschichte",
        "description": "Die wohl bekannteste Geschichte von Michael Ende gehört seit über 40 Jahren zu den wichtigsten deutschen Jugendgeschichten!\"Antiquariat“ steht auf der Glastür des kleinen Ladens, in den Bastian Balthasar Bux eines Tages hineingerät. Und hier stößt der Junge auf ein Buch, das sein Leben verändern wird: „Die unendliche Geschichte“.Das wunderbare Land Phantásien beginnt sich aufzulösen. Als die Kindliche Kaiserin davon erfährt, wird sie schwer krank. Der junge Atréju erhält den Auftrag, das Heilmit- tel für sie zu finden und Phantásien zu retten. Und nicht nur der Glücksdrache Fuchur hilft ihm dabei. Auch Bastian soll eine wichtige Rolle in der Geschichte des Buches spielen!",
        "titlelist": [
            "01 - Im Antiquariat",
            "02 - Phantásien in Not",
            "03 - Im Elfenbeinturm bei der Kindlichen Kaiserin",
            "04 - Atréjus Berufung",
            "05 - Die uralte Morla",
            "06 - Ygramul, die Viele",
            "07 - Atréju und der Glücksdrache Fuchur",
            "08 - Im Säulenwald bei Uyulála",
            "09 - Auf der Suche nach dem Menschenland",
            "10 - Bastian schließt das Buch"
        ],
        "runtime": "ca. 55 Minuten",
        "age_recommendation": "Ab 10 Jahre",
        "image": "https://res.cloudinary.com/tonies/image/fetch/f_auto,q_auto,c_fill,b_rgb:ffffff,w_1000,h_1200/https://278163f382d2bab4b036-4f5ec62496a160f3570d3b6e48fc4516.ssl.cf3.rackcdn.com/10000614-50001941-b-jm3fxX5U.png"
    },
    {
        "title": "Sterntaler und 4 weitere Märchen",
        "figure": "Lieblings-Märchen",
        "description": "Wie könnten wir diesen Tonie nicht sofort in unser Herz schließen - erzählt er doch so wunderbare Geschichten. Von einem kleinen Mädchen mit großem Mut und noch größerem Herzen, von einem liebenswerten, musikalischen Quartett, von hilfsbereiten Schwestern und unerschütterlicher Geschwisterliebe - und von wirklichen Glückstagen.",
        "titlelist": [
            "01 - Die Bremer Stadtmusikanten",
            "02 - Die sechs Schwäne",
            "03 - Hans im Glück",
            "04 - Sterntaler",
            "05 - Schneeweisschen und Rosenrot"
        ],
        "runtime": "ca. 50 Minuten",
        "age_recommendation": "Ab 3 Jahre",
        "image": "https://res.cloudinary.com/tonies/image/fetch/f_auto,q_auto,c_fill,b_rgb:ffffff,w_1000,h_1200/https://278163f382d2bab4b036-4f5ec62496a160f3570d3b6e48fc4516.ssl.cf3.rackcdn.com/10000137-50000691-b-Tje2BW-j.png"
    },
    {
        "title": "Die Waschbären sind los",
        "figure": "Bibi & Tina",
        "description": "Bibi, Tina und Alexander entdecken am Mühlenbach ein paar Waschbären, die ihnen auf den Martinshof folgen. Dort richten sie allerhand Unsinn an. Dennoch bittet der Förster Frau Martin darum, die Tiere zu beherbergen, bis er weiß, woher sie gekommen sind. Bibi und Tina übernehmen die Betreuung. Aber das ist gar nicht so einfach!",
        "titlelist": [
            "01 - Titellied",
            "02 - Die Überraschung am Mühlenbach",
            "03 - Waschbärenalarm",
            "04 - Auftrag vom Förster",
            "05 - Nichts als Ärger",
            "06 - Tina ist sauer",
            "07 - Ohne Ende Waschbären",
            "08 - Wo ist Woody?",
            "09 - Versöhnliches Ende"
        ],
        "runtime": "ca. 40 Minuten",
        "age_recommendation": "Ab 6 Jahre",
        "image": "https://res.cloudinary.com/tonies/image/fetch/f_auto,q_auto,c_fill,b_rgb:ffffff,w_1000,h_1200/https://278163f382d2bab4b036-4f5ec62496a160f3570d3b6e48fc4516.ssl.cf3.rackcdn.com/01-0114-98-0338-b-fM8SKAgm.png"
    },
    {
        "title": "Tierlieder",
        "figure": "Lieblings-Kinderlieder",
        "description": "Die besten Tierlieder - neu interpretiert und aufgefrischt!Ob auf der Mauer lauernde Wanzen, summende Bienen oder Affen, die durch den Wald rasen. Natürlich sind sie alle dabei, wenn das Kinderzimmer kurzeitig zum tanzenden Zoo wird oder man die Band mal eben mit auf Safari nehmen muss.22 Songs, also knapp 50 Minuten der bekannten Tierlieder ganz neu eingespielt mit den Minimusikern",
        "titlelist": [
            "01 - Die Affen rasen durch den Wald",
            "02 - Der Kuckuck und der Esel",
            "03 - Old MacDonald had a farm",
            "04 - Erst kommt der Sonnenkäferpapa",
            "05 - Seht die große Riesenschlange",
            "06 - Ich bin ein kleiner Esel",
            "07 - Häschen in der Grube",
            "08 - Mh, mh macht der grüne Frosch im Teich",
            "09 - Was müssen das für Bäume sein",
            "10 - Summ, summ, summ",
            "11 - Widewidewenne heißt meine Puthenne",
            "12 - Zwei kleine Wölfe",
            "13 - Alle Vögel sind schon da",
            "14 - Auf der Mauer, auf der Lauer",
            "15 - A, B, C, die Katze lief im Schnee",
            "16 - Alle meine Entchen",
            "17 - Kuckuck, Kuckuck",
            "18 - Das Krokodil vom Nil",
            "19 - Hopp, hopp, hopp",
            "20 - Das Katzentatzentanzspiel",
            "21 - Fuchs, du hast die Gans gestohlen",
            "22 - Die Vogelhochzeit"
        ],
        "runtime": "ca. 53 Minuten",
        "age_recommendation": "Ab 3 Jahre",
        "image": "https://res.cloudinary.com/tonies/image/fetch/f_auto,q_auto,c_fill,b_rgb:ffffff,w_1000,h_1200/https://278163f382d2bab4b036-4f5ec62496a160f3570d3b6e48fc4516.ssl.cf3.rackcdn.com/10001258-50003833-b--eXCs2PPc.png"
    },
    {
        "title": "Das Original-Hörspiel zu den Büchern 2",
        "figure": "Leo Lausemaus",
        "description": "Die kleine Maus mit großem HerzenSei dabei, wenn Leo Lausemaus vier neue Abenteuer erlebt. Du hörst, weshalb er nicht in den Kindergarten will und was geschieht, als seine Mama eines Tages zur Arbeit geht. Obendrein erfährst du, wie es für Leo ist, allein bei den Großeltern zu sein, und warum er sich ein Geschwisterchen wünscht.Viel Spaß!",
        "titlelist": [
            "01 - Will nicht in den Kindergarten",
            "02 - Mama geht zur Arbeit",
            "03 - Allein bei den Großeltern",
            "04 - Wünscht sich ein Geschwisterchen"
        ],
        "runtime": "ca. 50 Minuten",
        "age_recommendation": "Ab 3 Jahre",
        "image": "https://res.cloudinary.com/tonies/image/fetch/f_auto,q_auto,c_fill,b_rgb:ffffff,w_1000,h_1200/https://278163f382d2bab4b036-4f5ec62496a160f3570d3b6e48fc4516.ssl.cf3.rackcdn.com/01-0157-98-0499-b-2I-P8TJExeT.png"
    },
    {
        "title": "Volle Mähne!",
        "figure": "Die Haferhorde",
        "description": "Endlich bekommt Schoko Superpony Verstärkung: von seinem besten Freund Keks. Die beiden genießen das Leben auf dem Blümchenhof zwischen Hafer, Heu und Ausritten mit Lotte und Greta. Doch dann kommt die Chefin auf eine Idee, die den beiden Ponys gar nicht gefällt: sie plant eine Schnupper-Reitstunde.",
        "titlelist": [
            "01 - Kapitel 01: Volle Mähne!",
            "02 - Kapitel 02: Volle Mähne!",
            "03 - Kapitel 03: Volle Mähne!",
            "04 - Kapitel 04: Volle Mähne!",
            "05 - Kapitel 05: Volle Mähne!",
            "06 - Kapitel 06: Volle Mähne!",
            "07 - Kapitel 07: Volle Mähne!",
            "08 - Kapitel 08: Volle Mähne!",
            "09 - Kapitel 09: Volle Mähne!",
            "10 - Kapitel 10: Volle Mähne!",
            "11 - Kapitel 11: Volle Mähne!",
            "12 - Kapitel 12: Volle Mähne!",
            "13 - Kapitel 13: Volle Mähne!",
            "14 - Kapitel 14: Volle Mähne!",
            "15 - Kapitel 15: Volle Mähne!",
            "16 - Kapitel 15: Volle Mähne!",
            "17 - Kapitel 16: Volle Mähne!",
            "18 - Kapitel 17: Volle Mähne!",
            "19 - Kapitel 18: Volle Mähne!",
            "20 - Kapitel 19: Volle Mähne!",
            "21 - Kapitel 20: Volle Mähne!",
            "22 - Kapitel 21: Volle Mähne!",
            "23 - Kapitel 22: Volle Mähne!",
            "24 - Kapitel 23: Volle Mähne!",
            "25 - Kapitel 24: Volle Mähne!",
            "26 - Kapitel 25: Volle Mähne!",
            "27 - Kapitel 26: Volle Mähne!",
            "28 - Kapitel 27: Volle Mähne!",
            "29 - Kapitel 28: Volle Mähne!",
            "30 - Kapitel 29: Volle Mähne!",
            "31 - Kapitel 30: Volle Mähne!",
            "32 - Kapitel 31: Volle Mähne!",
            "33 - Kapitel 32: Volle Mähne!",
            "34 - Kapitel 33: Volle Mähne!",
            "35 - Kapitel 34: Volle Mähne!",
            "36 - Kapitel 35: Volle Mähne!",
            "37 - Kapitel 36: Volle Mähne!",
            "38 - Kapitel 37: Volle Mähne!",
            "39 - Kapitel 38: Volle Mähne!"
        ],
        "runtime": "ca. 121 Minuten",
        "age_recommendation": "Ab 8 Jahre",
        "image": "https://res.cloudinary.com/tonies/image/fetch/f_auto,q_auto,c_fill,b_rgb:ffffff,w_1000,h_1200/https://278163f382d2bab4b036-4f5ec62496a160f3570d3b6e48fc4516.ssl.cf3.rackcdn.com/01-0154-98-0464-b-w14AntYG.png"
    },
    {
        "title": "Pinocchio und 4 weitere Klassiker",
        "figure": "Lieblings-Klassiker",
        "description": "Fünf beliebte Klassiker der KinderliteraturAuf Daumengröße geschrumpft reist Nils Holgersson mit den Wildgänsen durch ganz Schweden. Hier trifft er viele verschiedene Tiere und erkennt, dass alle Lebewesen ein gutes Leben verdienen. Ach du Schreck, ein sprechender Holzklotz. Unter den Händen des Holzschnitzers Geppetto entsteht eine liebenswert-freche Holzfigur, die ihm als Erstes einfach die Zunge herausstreckt: Pinocchio. Neugierig folgt Alice einem seltsamen Kaninchen. Dabei stürzt sie plötzlich in ein Loch – sie fällt und fällt und fällt ... Wo wird sie bloß landen?Mowgli und seine Freunde Bagheera, Baloo und Kaa möchten eigentlich nur einen gemütlichen Tag im Dschungel verbringen. Aber ein kleines Äffchen macht ihnen einen Strich durch die Rechnung.Nach einem gewaltigen Sturm findet Dorothy sich in einem fremden Land wieder. Dort trifft sie auf den Strohmann, den Blechmann und den Löwen. Gemeinsam gehen sie zum Zauberer von Oz, denn er soll Dorothy den Weg zurück nach Hause zeigen können.",
        "titlelist": [
            "01 - Nils Holgersson",
            "02 - Pinocchio",
            "03 - Alice im Wunderland",
            "04 - Das Dschungelbuch",
            "05 - Der Zauberer von Oz"
        ],
        "runtime": "ca. 56 Minuten",
        "age_recommendation": "Ab 3 Jahre",
        "image": "https://res.cloudinary.com/tonies/image/fetch/f_auto,q_auto,c_fill,b_rgb:ffffff,w_1000,h_1200/https://278163f382d2bab4b036-4f5ec62496a160f3570d3b6e48fc4516.ssl.cf3.rackcdn.com/01-0120-98-0343-b-Q1howk5T.png"
    },
    {
        "title": "Die Schule der magischen Tiere",
        "figure": "Die Schule der magischen Tiere",
        "description": "Diese Schule birgt ein Geheimnis: Wer Glück hat,  findet hier den besten Freund, den es auf der Welt gibt. Ein magisches Tier, das sprechen kann! Wenn es zu dir gehört ...Der schüchterne Benni ist aufgeregt. Ausgerechnet ER soll ein magisches Tier bekommen, einen besten Freund, der immer hilft und mit dem man sprechen kann! Aber statt des wilden Raubtieres, das sich Benni gewünscht hat, blinzelt ihn Henrietta, die Schildkröte, aus ihrem Schuhkarton an ... Auch Ida hat ein magisches Tier bekommen. Ihr Fuchs Rabbat wird sofort ihr bester Freund! Endlich jemand zum Reden über das ätzende Referat mit dem langweiligen Benni oder über den coolen Jo, in den Ida ein bisschen verliebt ist ... Wie alles begann ... Die spannende Hörspielfassung des ersten Bandes der beliebten Bestseller-Reihe von Margit Auer!",
        "titlelist": [
            "01 - Titellied „Willkommen in der Schule der magischen Tiere“",
            "02 - Pinguin Juri",
            "03 - Der Umzugswagen",
            "04 - Tante Elfriiiede!",
            "05 - Der geheimnisvolle Omnibus",
            "06 - Sportstunde",
            "07 - Gesta en, Morrison",
            "08 - Pinkie sorgt für Chaos",
            "09 - Alles läuft schief",
            "10 - Post von der magischen Zoohandlung",
            "11 - Ida und Benni bekommen ihre magischen Tiere",
            "12 - Zu Hause bei Ida",
            "13 - Zu Hause bei Benni",
            "14 - Die magischen Tiere kommen mit in die Schule",
            "15 - Rabbat hat Appetit auf Schokokekse",
            "16 - Dicke Luft in der Pausenhalle",
            "17 - Der Liebesbrief",
            "18 - Der stinkende Zaubertrank",
            "19 - Ausflug durch die Nacht",
            "20 - Ertappt!",
            "21 - Die Stinkebrühe landet im Müll",
            "22 - Der Wettkampf",
            "23 - Jo und Juri",
            "24 - Madagaskar",
            "25 - Titellied „Willkommen in der Schule der magischen Tiere“"
        ],
        "runtime": "ca. 82 Minuten",
        "age_recommendation": "Ab 7 Jahre",
        "image": "https://res.cloudinary.com/tonies/image/fetch/f_auto,q_auto,c_fill,b_rgb:ffffff,w_1000,h_1200/https://278163f382d2bab4b036-4f5ec62496a160f3570d3b6e48fc4516.ssl.cf3.rackcdn.com/01-0100-98-0322-b-FrJN465A.png"
    },
    {
        "title": "(M)auserlesene Lieder",
        "figure": "Maus",
        "description": "",
        "titlelist": [
            "01 - Begrüßung deutsch",
            "02 - Begrüßung singhalesisch",
            "03 - Mausspot: Es war einmal die Maus",
            "04 - Nulli und Priesemut: Freundschaftslied",
            "05 - Ohrwurm",
            "06 - Ballade von Herrn Gelb und Frau Blau",
            "07 - Zauberer Korinthe",
            "08 - Schweinchen Firlefanz",
            "09 - Jule wäscht sich nie",
            "10 - Heinz, der Elefant",
            "11 - Hier kommt die Maus",
            "12 - Meine Oma fährt im Hühnerstall Motorrad",
            "13 - Das Erfinderlied",
            "14 - Mann und Bär im Meer",
            "15 - Wo schlafen Bärenkinder?",
            "16 - Mausspot: Räuberleiter",
            "17 - Verabschiedung"
        ],
        "runtime": "ca. 40 Minuten",
        "age_recommendation": "Ab 3 Jahre",
        "image": "https://res.cloudinary.com/tonies/image/fetch/f_auto,q_auto,c_fill,b_rgb:ffffff,w_1000,h_1200/https://278163f382d2bab4b036-4f5ec62496a160f3570d3b6e48fc4516.ssl.cf3.rackcdn.com/01-0006-b-VBRoor9F.png"
    },
    {
        "title": "Ein Geburtstagsfest für Lieselotte und andere Geschichten",
        "figure": "Lieselotte",
        "description": "Diese Kuh macht einfach glücklich! Die Kuh Lieselotte hat es manchmal ganz schön schwer: Sie hat Geburtstag, aber niemand auf dem Bauernhof scheint davon Notiz zu nehmen. Oder sie wird krank und muss das Stroh hüten, während die anderen Tiere draußen Drachen steigen lassen. Oder ein Paket der Bäuerin geht verloren, das Lieselotte transportieren sollte ...Wer Lieselotte kennt, der weiß, dass die kleinen Tücken des Alltags für viele lustige Turbulenzen sorgen und dass am Ende doch alles gut wird.",
        "titlelist": [
            "01 - Ein Geburtstagsfest für Lieselotte 1",
            "02 - Ein Geburtstagsfest für Lieselotte 2",
            "03 - Ein Geburtstagsfest für Lieselotte 3",
            "04 - Lieselotte sucht 1",
            "05 - Lieselotte sucht 2",
            "06 - Lieselotte sucht 3",
            "07 - Lieselotte sucht 4",
            "08 - Lieselotte ist krank 1",
            "09 - Lieselotte ist krank 2",
            "10 - Lieselotte ist krank 3"
        ],
        "runtime": "ca. 57 Minuten",
        "age_recommendation": "Ab 3 Jahre",
        "image": "https://res.cloudinary.com/tonies/image/fetch/f_auto,q_auto,c_fill,b_rgb:ffffff,w_1000,h_1200/https://278163f382d2bab4b036-4f5ec62496a160f3570d3b6e48fc4516.ssl.cf3.rackcdn.com/01-0127-98-0349-b-wNXyNeLt.png"
    },
    {
        "title": "Die besten Spiel- und Bewegungslieder",
        "figure": "Lichterkinder",
        "description": "Jedes Kind auf der Welt ist ein Lichterkind„Der Körperteil Blues“ von Lichterkinder, wer kennt ihn nicht? Mit mehr als 40 Millionen Aufrufen bei YouTube ist das Lied der neue Hit in den Kitas und Kinderzimmern Deutschlands! „Lichterkinder“ steht für neue, frische und moderne Kinderlieder, die Spaß machen und gleichzeitig auf spielerische Art und Weise Lerninhalte und Werte vermitteln. Auf mittlerweile 7 Lichterkinder Alben sind die Kinder selbst der Star. Gesungen und präsentiert werden die Lieder auf Augenhöhe von Kindern für Kinder. Jeder kann mitsingen und mitmachen, denn: Jedes Kind auf der Welt ist ein Lichterkind!Das Album Lichterkinder – Die besten Spiel- und Bewegungslieder ist exklusiv als Tonie erhältlich und eine spezielle Zusammenstellung der größten Hits der Lichterkinder. Und obendrauf gibt es nur in dieser Sammlung als Extratitel das Lied „Liki & die Tonies“!",
        "titlelist": [
            "01 - Der Körperteil Blues",
            "02 - Samba, Rumba, Cha Cha Cha",
            "03 - Guck mal diese Biene da",
            "04 - Liki & die Tonies",
            "05 - Gehen wie ein Roboter",
            "06 - Ich bin groß",
            "07 - Stampf und Klatsch",
            "08 - Große Chaoten",
            "09 - Kinderpartyeisenbahn",
            "10 - Das ABC der Tiere",
            "11 - Tanzen wie der Eisbär",
            "12 - Alle Kinder haben Träume",
            "13 - Mexiko, Mexiko",
            "14 - Du schaffst das",
            "15 - Wir räumen auf",
            "16 - Fünf kleine Fische",
            "17 - Dumdideldum",
            "18 - Astronautengeburtstag",
            "19 - Danke Mama",
            "20 - Lichterkinder"
        ],
        "runtime": "ca. 50 Minuten",
        "age_recommendation": "Ab 3 Jahre",
        "image": "https://res.cloudinary.com/tonies/image/fetch/f_auto,q_auto,c_fill,b_rgb:ffffff,w_1000,h_1200/https://278163f382d2bab4b036-4f5ec62496a160f3570d3b6e48fc4516.ssl.cf3.rackcdn.com/10000492-50001549-b-bUCDWsVq.png"
    },
    {
        "title": "Die Reise zum Großvater",
        "figure": "Heidi",
        "description": "Heidi ist aufgeregt. Morgen wird sie zu ihrem Großvater in die Berge ziehen. Er lebt auf einer Alm zwischen bunten Wiesen und schneebedeckten Gipfeln. Es ist wunderschön dort. Doch der Alm-Öhi, wie die Dorfbewohner den Großvater nennen, ist es nicht gewohnt, Besuch zu haben. Er spricht kaum ein Wort mit Heidi. Mit den Tieren auf der Alm schließt sie dagegen schon am ersten Tag Freundschaft …",
        "titlelist": [
            "01 - Titellied \"Heidi\"",
            "02 - Die Reise zum Großvater",
            "03 - Alte Bekannte",
            "04 - Ein Schmetterling",
            "05 - Großvaters Hütte",
            "06 - Der erste Tag auf der Alm",
            "07 - Ziegen hüten",
            "08 - Melken - der zweite Versuch",
            "09 - Zurück auf der Weide",
            "10 - Die Mutprobe",
            "11 - Bernie - Retter in der Not",
            "12 - Unerwarteter Besuch",
            "13 - Gerettet!"
        ],
        "runtime": "ca. 60 Minuten",
        "age_recommendation": "Ab 5 Jahre",
        "image": "https://res.cloudinary.com/tonies/image/fetch/f_auto,q_auto,c_fill,b_rgb:ffffff,w_1000,h_1200/https://278163f382d2bab4b036-4f5ec62496a160f3570d3b6e48fc4516.ssl.cf3.rackcdn.com/01-0032-98-0108-b-Sdcz5OyY.png"
    }
]